README.md
setup.cfg
setup.py
eis/__init__.py
eis/auth/__init__.py
eis/auth/api_client.py
eis/auth/configuration.py
eis/auth/exceptions.py
eis/auth/model_utils.py
eis/auth/rest.py
eis/auth/api/__init__.py
eis/auth/api/authservice_api.py
eis/auth/api/default_api.py
eis/auth/api/workspaces_api.py
eis/auth/apis/__init__.py
eis/auth/model/__init__.py
eis/auth/model/create_org_and_user_request_dto.py
eis/auth/model/create_org_and_user_response_class.py
eis/auth/model/create_user_request_dto.py
eis/auth/model/create_user_response_class.py
eis/auth/model/custom_schema_class.py
eis/auth/model/forgot_password_request_dto.py
eis/auth/model/get_saml_login_link_request_dto.py
eis/auth/model/inline_response200.py
eis/auth/model/inline_response503.py
eis/auth/model/list_workspaces_response_class.py
eis/auth/model/login_by_saml_request_dto.py
eis/auth/model/login_class.py
eis/auth/model/login_request_dto.py
eis/auth/model/logout_request_dto.py
eis/auth/model/org_invitation_class.py
eis/auth/model/organization_class.py
eis/auth/model/refresh_token_dto.py
eis/auth/model/reset_password_request_dto.py
eis/auth/model/role_class.py
eis/auth/model/switch_workspace_request_without_refresh_token_dto.py
eis/auth/model/switch_workspace_response_class.py
eis/auth/model/user_class.py
eis/auth/model/verify_org_invitation_request_dto.py
eis/auth/model/verify_org_invitation_response_class.py
eis/auth/model/workspace_class.py
eis/auth/models/__init__.py
eis_auth.egg-info/PKG-INFO
eis_auth.egg-info/SOURCES.txt
eis_auth.egg-info/dependency_links.txt
eis_auth.egg-info/requires.txt
eis_auth.egg-info/top_level.txt
test/test_authservice_api.py
test/test_create_org_and_user_request_dto.py
test/test_create_org_and_user_response_class.py
test/test_create_user_request_dto.py
test/test_create_user_response_class.py
test/test_custom_schema_class.py
test/test_default_api.py
test/test_forgot_password_request_dto.py
test/test_get_saml_login_link_request_dto.py
test/test_inline_response200.py
test/test_inline_response503.py
test/test_list_workspaces_response_class.py
test/test_login_by_saml_request_dto.py
test/test_login_class.py
test/test_login_request_dto.py
