Metadata-Version: 2.1
Name: eis-auth
Version: 1.18.0
Summary: EMIL AuthService
Home-page: UNKNOWN
Author: Contact us
Author-email: kontakt@emil.de
License: UNKNOWN
Keywords: OpenAPI,OpenAPI-Generator,EMIL AuthService
Platform: UNKNOWN
Requires-Python: >=3.6
